textAnalyzerPy/__init__.py
textAnalyzerPy/textAnalyzerPy.py
TextAnalyzerPy-0.0.1.dist-info/METADATA
TextAnalyzerPy-0.0.1.dist-info/WHEEL
TextAnalyzerPy-0.0.1.dist-info/top_level.txt
TextAnalyzerPy-0.0.1.dist-info/RECORD
