Metadata-Version: 2.1
Name: TextAnalyzerPy
Version: 0.0.1
Summary: oss-dev TextAnalyzerPy
Home-page: https://github.com/erase-jeong/TextAnalyzerPy
Download-URL: https://github.com/erase-jeong/TextAnalyzerPy/archive/refs/tags/v0.0.1.zip
Author: jiwoojeong
Author-email: erase.jeong@gmail.com
Classifier: Programming Language :: Python :: 3
Classifier: Operating System :: OS Independent
Requires-Dist: pytest
